ndx_lflab_novela/__init__.py
ndx_lflab_novela/apparatus.py
ndx_lflab_novela/fl_electrode_group.py
ndx_lflab_novela/header_device.py
ndx_lflab_novela/ntrode.py
ndx_lflab_novela/probe.py
ndx_lflab_novela/spec/ndx-lflab-novela.extensions.yaml
ndx_lflab_novela/spec/ndx-lflab-novela.namespace.yaml
tests/__init__.py
tests/test_apparatus.py
tests/test_edge.py
tests/test_fl_electrode_group.py
tests/test_header_device.py
tests/test_node.py
tests/test_ntrode.py
tests/test_probe.py
ndx_lflab_novela-0.0.1.dist-info/LICENSE.txt
ndx_lflab_novela-0.0.1.dist-info/METADATA
ndx_lflab_novela-0.0.1.dist-info/WHEEL
ndx_lflab_novela-0.0.1.dist-info/top_level.txt
ndx_lflab_novela-0.0.1.dist-info/RECORD
