Metadata-Version: 2.1
Name: ndx-lflab-novela
Version: 0.0.1
Summary: NovelaNeurotechnologies Namespaces
Home-page: UNKNOWN
Author: NovelaDevops
Author-email: devops@novelaneuro.com
License: BSD 3-Clause
Platform: UNKNOWN
Classifier: Intended Audience :: Developers
Classifier: Intended Audience :: Science/Research
Requires-Dist: pynwb (>=1.1.2)
Requires-Dist: hdmf (==1.3.3)
